pylintsql/__init__.py
pylintsql/cli.py
pylintsql/pylintsql.py
pylintsql/utils/__init__.py
pylintsql/utils/arg_utils.py
pylintsql/utils/config_utils.py
pylintsql/utils/sql_utils.py
pylintsql-0.0.9.dist-info/METADATA
pylintsql-0.0.9.dist-info/WHEEL
pylintsql-0.0.9.dist-info/entry_points.txt
pylintsql-0.0.9.dist-info/licenses/LICENSE
pylintsql-0.0.9.dist-info/RECORD
