Metadata-Version: 2.4
Name: pylintsql
Version: 0.0.9
Summary: a tool that lints/fixes SQL code within Python strings using SQLFluff
Project-URL: Homepage, https://github.com/mgs-mnlngt/pylintsql
Author-email: Mark Manlangit <mgs.manlangit@gmail.com>
License-Expression: MIT
License-File: LICENSE
Classifier: License :: OSI Approved :: MIT License
Classifier: Operating System :: OS Independent
Classifier: Programming Language :: Python :: 3.12
Requires-Python: >=3.0
Requires-Dist: libcst>=0.4.0
Requires-Dist: pathspec>=0.9.0
Requires-Dist: sqlfluff>=3.3.1
Requires-Dist: toml>=0.10.2
